{"mjF1wMvQ1G7Tde+q1aVqIQ==":"mbr-1014x625.jpg","B3G7psSNHrNx76zE7qRIXg==":"mbr-1920x1281.jpg","aHuGNFS1Af6BDIhLBzQ6YQ==":"cod%20black%20ops%203-696x698.jpg","RM/HwvINJJ+bd83M0dQi5A==":"trialt%20generic_logo-122x40.png","1T5c5fxU8EpGQtDWxVVm1A==":"trialt%20generic_logo-292x95.png","TYsxLjOEBZJKH9dXMXHc+g==":"trialt%20generic_logo-292x95.png","RZZSjKGzs9ysYgULPlPTSQ==":"guardian%20grootjpg-696x698.jpg","Ro8HTmyxdYV+cTzUI8N42Q==":"mbr-1920x1184.jpg","Poc4GcF07HuYMSTtcTpmag==":"iam%20groot%201-696x698.jpg","NnDuvNiTp/qdGVPN5am2aA==":"voltus%201-696x698.png","PHxw7wNFLEQjNn4TiNetAQ==":"voltus%202%20hangin-696x698.jpg","PxHRXIvjEp37E3hjuMNQFw==":"hulk%20hand-696x698.png","krMhjEQu/5s1uuLNEQEmdg==":"hulk%20hand-696x698.png","00zZUyXhpQoaC0uKo25qvA==":"product1.jpg","OP97CjHFXcFHS5nZi6tWDA==":"rossi%20shark-696x698.jpg","dmqFTQIW4zlZ70wvKREuqA==":"5722421_b8995833-f889-4ca1-8e80-a2d3f189187e_802-802-696x696.png","E5qGFl25fDnDIesoEWcGEw==":"5722421_517e4adb-b16e-45d7-8d68-eda5ffdd32a2-970x513.png","pA/0fZrGEQ/YNzfmBtibgA==":"cod%20black%20ops%203-990x993.jpg","N3WmJBVZe6lJ0+LDv7G3Wg==":"cod%20black%20ops%203%20folded-900x900.jpg","pa5Dkwo/T1qgW/t0h+fQvA==":"background5.jpg","R8+CpA1dX2Pwj6pviPk1uw==":"5722421_01c5b99a-eb83-48be-a307-76d2d108513b_903-903-696x696.png","RvhAmw8xflgGshnzXcu1nw==":"guardian%20grootjpg-990x993.jpg","jC9K071bf3CVfZ6JqRwelg==":"guardian%20groot%20folded-900x900.jpg"}